LICENSE
MANIFEST.in
README.md
setup.py
pythools/__init__.py
pythools/github_api.py
pythools.egg-info/PKG-INFO
pythools.egg-info/SOURCES.txt
pythools.egg-info/dependency_links.txt
pythools.egg-info/not-zip-safe
pythools.egg-info/requires.txt
pythools.egg-info/top_level.txt